logonlabs/__init__.py
logonlabs/allowableValues.py
logonlabs/api.py
logonlabs/client.py
logonlabs_python-1.7.7.dist-info/LICENSE
logonlabs_python-1.7.7.dist-info/METADATA
logonlabs_python-1.7.7.dist-info/WHEEL
logonlabs_python-1.7.7.dist-info/top_level.txt
logonlabs_python-1.7.7.dist-info/RECORD
