Metadata-Version: 2.1
Name: logonlabs-python
Version: 1.7.7
Summary: Logonlabs Python package
Home-page: https://github.com/logonlabs/logonlabs-python
Author: Edward Guan
Author-email: eguan@logonlabs.com
License: UNKNOWN
Platform: UNKNOWN
Classifier: Programming Language :: Python :: 3
Classifier: Operating System :: OS Independent
